{
  "todayForecastPeakDemandTS": "20210708183000",
  "AvailableCapacity": 49268,
  "currentWind": 636,
  "Limitation": 0,
  "CurrentSystemDemandWithoutPump": 32205,
  "histDemand": "50,270 MW",
  "TodaysPeakDemand": 32834,
  "slotDate": "07/08/2021 12:00",
  "gridstatus": [
    "Normal"
  ],
  "currentCo2intensity": 0.21691996849001827,
  "CurrentNetDemandWithoutPump": 19258,
  "histDemandDate": "Jul 24, 2006",
  "CurrentNetDemand": 19824,
  "CurrentSystemDemand": 32834,
  "Shutdown": 0,
  "HistoryFirstDate": "20180410",
  "CurrentAdjustedUnloadedGenerationCapacityTS": "20210708115956",
  "CurrentSystemDemandWithoutPumpTS": "20210708115811",
  "currentRenewableswoBatteries": 14657,
  "TodaysPeakDemandTS": "20210708115956",
  "currentRenewables": 14906,
  "CurrentNetDemandTS": "20210708115811",
  "CurrentAdjustedUnloadedGenerationCapacity": 16434,
  "renewablesPercent": 45,
  "CurrentNetDemandWithoutPumpTS": "20210708115811",
  "tomorrowsForecastPeakDemand": 42655,
  "PS_VERSION": "1.26b",
  "CurrentSystemDemandTS": null,
  "currentSolar": 12315,
  "renewablesPercentwoBatteries": 45,
  "OutageDTS": null,
  "currentCo2": 7122,
  "todayForecastPeakDemand": 40422
}
