{
  "Unloaded_capacity_derated_max": 19090,
  "todayForecastPeakDemand": 41625,
  "Unloaded_capacity_1H": 6163,
  "Shutdown": "2501.37",
  "currentRenewablesHybrid": null,
  "CurrentSystemDemandWithoutPump": 41573,
  "Required_reserve": 2541,
  "currentCoalCO2": 0,
  "Current_reserve": 3534,
  "currentBiomassCO2": 159,
  "currentOther": 0,
  "HistoryFirstDate": "20180410",
  "currentNuclear": 2263,
  "currentGeothermal": 783,
  "tomorrowsForecastPeakDemand": 37984,
  "Limitation": "2990.98",
  "currentSolar": 5981,
  "TodaysPeakDemandTS": "20240719184020",
  "currentImports": 679,
  "currentNaturalGasCO2": 8650,
  "CurrentAdjustedUnloadedGenerationCapacityTS": "20240719184956",
  "currentBiogasCO2": 97,
  "currentSolarHybrids": 613,
  "Unloaded_capacity_10M": 4891,
  "currentRenewables": 10886,
  "currentWindHybrids": 0,
  "currentCo2": 8902,
  "currentImportsCO2": 263,
  "CurrentSystemDemandWithoutPumpTS": "20240719184811",
  "Available_capacity": 46523,
  "todayForecastPeakDemandTS": "20240719190000",
  "currentLargeHydro": 4277,
  "CurrentNetDemandWithoutPumpTS": "20240719184811",
  "CurrentNetDemandWithoutPump": 33179,
  "hybridsPercent": 2.6,
  "currentWind": 2820,
  "currentGeothermalCO2": 8,
  "CurrentSystemDemand": 41631,
  "currentBiomass": 345,
  "currentNonRenewableHybrid": null,
  "CurrentSystemDemandTS": "20240719184956",
  "currentNaturalGas": 18803,
  "histDemand": "52,061 MW",
  "histDemandDate": "Sep 6, 2022",
  "CurrentAdjustedUnloadedGenerationCapacity": 14079,
  "CurrentSystemDemandPlusUnloaded4h": 51947,
  "gridstatus": [
    "Normal"
  ],
  "slotDate": "07/19/2024 18:50",
  "renewablesPercentwoBatteries": 26,
  "currentBatteriesStandalone": 4725,
  "currentCoal": 0,
  "currentBiogas": 178,
  "currentBatteriesHybrid": 416,
  "currentSmallHydro": 281,
  "AvailableCapacity": 55710,
  "currentHybrids": 1060,
  "PS_VERSION": "1.26b",
  "Unloaded_capacity_4H": 10316,
  "renewablesPercent": 26,
  "CurrentNetDemand": 33270,
  "currentBatteries": 5054,
  "CurrentNetDemandTS": "20240719184811",
  "OutageDTS": "07/17/2019 23:30:00 (PPT)",
  "currentRenewableswoBatteries": 10886,
  "currentCo2intensity": 0.2138362966540204,
  "TodaysPeakDemand": 41799
}
