{
  "Unloaded_capacity_derated_max": 30683,
  "todayForecastPeakDemand": 29927,
  "Unloaded_capacity_1H": 9680,
  "Shutdown": "2501.37",
  "currentRenewablesHybrid": null,
  "CurrentSystemDemandWithoutPump": 28521,
  "Required_reserve": 1617,
  "currentCoalCO2": -1,
  "Current_reserve": 2308,
  "currentBiomassCO2": 128,
  "currentOther": 0,
  "HistoryFirstDate": "20180410",
  "currentNuclear": 2246,
  "currentGeothermal": 773,
  "tomorrowsForecastPeakDemand": 28812,
  "Limitation": "2990.98",
  "currentSolar": -44,
  "TodaysPeakDemandTS": "20241015184512",
  "currentImports": 5702,
  "currentNaturalGasCO2": 4403,
  "CurrentAdjustedUnloadedGenerationCapacityTS": "20241015200956",
  "currentBiogasCO2": 89,
  "currentSolarHybrids": -2,
  "Unloaded_capacity_10M": 5902,
  "currentRenewables": 5251,
  "currentWindHybrids": 0,
  "currentCo2": 7189,
  "currentImportsCO2": 2473,
  "CurrentSystemDemandWithoutPumpTS": "20241015200811",
  "Available_capacity": 34706,
  "todayForecastPeakDemandTS": "20241015190000",
  "currentLargeHydro": 2283,
  "CurrentNetDemandWithoutPumpTS": "20241015200811",
  "CurrentNetDemandWithoutPump": 24761,
  "hybridsPercent": 1.6,
  "currentWind": 3806,
  "currentGeothermalCO2": 7,
  "CurrentSystemDemand": 28804,
  "currentBiomass": 297,
  "currentNonRenewableHybrid": null,
  "CurrentSystemDemandTS": "20241015200956",
  "currentNaturalGas": 10193,
  "histDemand": "52,061 MW",
  "histDemandDate": "Sep 6, 2022",
  "CurrentAdjustedUnloadedGenerationCapacity": 19794,
  "CurrentSystemDemandPlusUnloaded4h": 45509,
  "gridstatus": [
    "Normal"
  ],
  "slotDate": "10/15/2024 20:10",
  "renewablesPercentwoBatteries": 18,
  "currentBatteriesStandalone": 3006,
  "currentCoal": -1,
  "currentBiogas": 173,
  "currentBatteriesHybrid": 415,
  "currentSmallHydro": 219,
  "AvailableCapacity": 48598,
  "currentHybrids": 450,
  "PS_VERSION": "1.26b",
  "Unloaded_capacity_4H": 16705,
  "renewablesPercent": 18,
  "CurrentNetDemand": 25054,
  "currentBatteries": 3450,
  "CurrentNetDemandTS": "20241015200811",
  "OutageDTS": "07/17/2019 23:30:00 (PPT)",
  "currentRenewableswoBatteries": 5251,
  "currentCo2intensity": 0.2495792984612733,
  "TodaysPeakDemand": 30073
}
