{
  "Unloaded_capacity_derated_max": 38404,
  "todayForecastPeakDemand": 27343,
  "Unloaded_capacity_1H": 10139,
  "Shutdown": "2501.37",
  "currentRenewablesHybrid": null,
  "CurrentSystemDemandWithoutPump": 23444,
  "Required_reserve": 1534,
  "currentCoalCO2": -1,
  "Current_reserve": 2617,
  "currentBiomassCO2": 94,
  "currentOther": 0,
  "HistoryFirstDate": "20180410",
  "currentNuclear": 2244,
  "currentGeothermal": 801,
  "tomorrowsForecastPeakDemand": 29171,
  "Limitation": "2990.98",
  "currentSolar": 14947,
  "TodaysPeakDemandTS": "20241013155428",
  "currentImports": -821,
  "currentNaturalGasCO2": 1783,
  "CurrentAdjustedUnloadedGenerationCapacityTS": "20241013155456",
  "currentBiogasCO2": 90,
  "currentSolarHybrids": 1196,
  "Unloaded_capacity_10M": 7703,
  "currentRenewables": 18262,
  "currentWindHybrids": 0,
  "currentCo2": 1616,
  "currentImportsCO2": -372,
  "CurrentSystemDemandWithoutPumpTS": "20241013155411",
  "Available_capacity": 32178,
  "todayForecastPeakDemandTS": "20241013190000",
  "currentLargeHydro": 689,
  "CurrentNetDemandWithoutPumpTS": "20241013155411",
  "CurrentNetDemandWithoutPump": 7614,
  "hybridsPercent": 5.6,
  "currentWind": 1938,
  "currentGeothermalCO2": 7,
  "CurrentSystemDemand": 24475,
  "currentBiomass": 215,
  "currentNonRenewableHybrid": null,
  "CurrentSystemDemandTS": "20241013155456",
  "currentNaturalGas": 4064,
  "histDemand": "52,061 MW",
  "histDemandDate": "Sep 6, 2022",
  "CurrentAdjustedUnloadedGenerationCapacity": 27360,
  "CurrentSystemDemandPlusUnloaded4h": 45660,
  "gridstatus": [
    "Normal"
  ],
  "slotDate": "10/13/2024 15:55",
  "renewablesPercentwoBatteries": 75,
  "currentBatteriesStandalone": -750,
  "currentCoal": -1,
  "currentBiogas": 172,
  "currentBatteriesHybrid": 120,
  "currentSmallHydro": 173,
  "AvailableCapacity": 51835,
  "currentHybrids": 1366,
  "PS_VERSION": "1.26b",
  "Unloaded_capacity_4H": 21185,
  "renewablesPercent": 75,
  "CurrentNetDemand": 8773,
  "currentBatteries": -592,
  "CurrentNetDemandTS": "20241013155411",
  "OutageDTS": "07/17/2019 23:30:00 (PPT)",
  "currentRenewableswoBatteries": 18262,
  "currentCo2intensity": 0.06602015483657418,
  "TodaysPeakDemand": 24482
}
