{
  "CurrentNetDemandWithoutPumpTS": "20220112215811",
  "slotDate": "01/12/2022 22:00",
  "renewablesPercentwoBatteries": 10,
  "histDemand": "50,270 MW",
  "CurrentSystemDemandWithoutPumpTS": "20220112215811",
  "Available_capacity": 32723,
  "histDemandDate": "Jul 24, 2006",
  "Required_reserve": 2220,
  "CurrentSystemDemandTS": "20220112220000",
  "TodaysPeakDemandTS": "20220112175516",
  "Unloaded_capacity_4H": 13375,
  "Unloaded_capacity_10M": 7937,
  "currentRenewables": 2550,
  "Limitation": "2990.98",
  "PS_VERSION": "1.26b",
  "AvailableCapacity": 40443,
  "renewablesPercent": 10,
  "CurrentAdjustedUnloadedGenerationCapacityTS": "20220112220000",
  "todayForecastPeakDemandTS": "20220112174500",
  "currentCo2intensity": 0.34990256029882233,
  "todayForecastPeakDemand": 28360,
  "currentSolar": -26,
  "CurrentSystemDemand": 24786,
  "currentCo2": 8673,
  "CurrentAdjustedUnloadedGenerationCapacity": 15657,
  "OutageDTS": "07/17/2019 23:30:00 (PPT)",
  "HistoryFirstDate": "20180410",
  "CurrentNetDemandWithoutPump": 24002,
  "Shutdown": "2501.37",
  "Unloaded_capacity_1H": 11910,
  "Unloaded_capacity_derated_nax": 30788,
  "TodaysPeakDemand": 28472,
  "currentWind": 828,
  "tomorrowsForecastPeakDemand": 27967,
  "CurrentNetDemandTS": "20220112215811",
  "CurrentNetDemand": 24106,
  "currentRenewableswoBatteries": 2439,
  "gridstatus": [
    "Normal"
  ],
  "Current_reserve": 2762,
  "CurrentSystemDemandWithoutPump": 24734
}
