{
  "Unloaded_capacity_derated_max": 34430,
  "todayForecastPeakDemand": 28673,
  "Unloaded_capacity_1H": 9449,
  "Shutdown": "2501.37",
  "currentRenewablesHybrid": null,
  "CurrentSystemDemandWithoutPump": 28057,
  "Required_reserve": 1609,
  "currentCoalCO2": 0,
  "Current_reserve": 2484,
  "currentBiomassCO2": 128,
  "currentOther": 0,
  "HistoryFirstDate": "20180410",
  "currentNuclear": 1140,
  "currentGeothermal": 660,
  "tomorrowsForecastPeakDemand": 28009,
  "Limitation": "2990.98",
  "currentSolar": 376,
  "TodaysPeakDemandTS": "20240515195608",
  "currentImports": 4511,
  "currentNaturalGasCO2": 2378,
  "CurrentAdjustedUnloadedGenerationCapacityTS": "20240515205956",
  "currentBiogasCO2": 91,
  "currentSolarHybrids": -2,
  "Unloaded_capacity_10M": 6490,
  "currentRenewables": 7922,
  "currentWindHybrids": 0,
  "currentCo2": 4674,
  "currentImportsCO2": 2034,
  "CurrentSystemDemandWithoutPumpTS": "20240515205811",
  "Available_capacity": 34541,
  "todayForecastPeakDemandTS": "20240515203000",
  "currentLargeHydro": 4931,
  "CurrentNetDemandWithoutPumpTS": "20240515205811",
  "CurrentNetDemandWithoutPump": 21563,
  "hybridsPercent": 1.1,
  "currentWind": 6127,
  "currentGeothermalCO2": 6,
  "CurrentSystemDemand": 28052,
  "currentBiomass": 290,
  "currentNonRenewableHybrid": null,
  "CurrentSystemDemandTS": "20240515205956",
  "currentNaturalGas": 5355,
  "histDemand": "52,061 MW",
  "histDemandDate": "Sep 6, 2022",
  "CurrentAdjustedUnloadedGenerationCapacity": 16954,
  "CurrentSystemDemandPlusUnloaded4h": 42169,
  "gridstatus": [
    "Normal"
  ],
  "slotDate": "05/15/2024 21:00",
  "renewablesPercentwoBatteries": 28,
  "currentBatteriesStandalone": 4367,
  "currentCoal": 0,
  "currentBiogas": 171,
  "currentBatteriesHybrid": 312,
  "currentSmallHydro": 337,
  "AvailableCapacity": 45006,
  "currentHybrids": 321,
  "PS_VERSION": "1.26b",
  "Unloaded_capacity_4H": 14117,
  "renewablesPercent": 28,
  "CurrentNetDemand": 21599,
  "currentBatteries": 4637,
  "CurrentNetDemandTS": "20240515205811",
  "OutageDTS": "07/17/2019 23:30:00 (PPT)",
  "currentRenewableswoBatteries": 7922,
  "currentCo2intensity": 0.1666097955861071,
  "TodaysPeakDemand": 28651
}
