{
  "Unloaded_capacity_derated_max": 36923,
  "todayForecastPeakDemand": 25485,
  "Unloaded_capacity_1H": 9793,
  "Shutdown": "2501.37",
  "currentRenewablesHybrid": null,
  "CurrentSystemDemandWithoutPump": 20672,
  "Required_reserve": 1190,
  "currentCoalCO2": 0,
  "Current_reserve": 1694,
  "currentBiomassCO2": 44,
  "currentOther": 0,
  "HistoryFirstDate": "20180410",
  "currentNuclear": 1139,
  "currentGeothermal": 779,
  "tomorrowsForecastPeakDemand": 24575,
  "Limitation": "2990.98",
  "currentSolar": 46,
  "TodaysPeakDemandTS": "20240425000056",
  "currentImports": 4915,
  "currentNaturalGasCO2": 1934,
  "CurrentAdjustedUnloadedGenerationCapacityTS": "20240425051956",
  "currentBiogasCO2": 83,
  "currentSolarHybrids": -3,
  "Unloaded_capacity_10M": 5933,
  "currentRenewables": 5670,
  "currentWindHybrids": 0,
  "currentCo2": 4349,
  "currentImportsCO2": 2303,
  "CurrentSystemDemandWithoutPumpTS": "20240425051811",
  "Available_capacity": 26704,
  "todayForecastPeakDemandTS": "20240425203000",
  "currentLargeHydro": 4142,
  "CurrentNetDemandWithoutPumpTS": "20240425051811",
  "CurrentNetDemandWithoutPump": 16279,
  "hybridsPercent": 0,
  "currentWind": 4303,
  "currentGeothermalCO2": 8,
  "CurrentSystemDemand": 20771,
  "currentBiomass": 93,
  "currentNonRenewableHybrid": null,
  "CurrentSystemDemandTS": "20240425051956",
  "currentNaturalGas": 4164,
  "histDemand": "52,061 MW",
  "histDemandDate": "Sep 6, 2022",
  "CurrentAdjustedUnloadedGenerationCapacity": 19663,
  "CurrentSystemDemandPlusUnloaded4h": 38659,
  "gridstatus": [
    "Normal"
  ],
  "slotDate": "04/25/2024 05:20",
  "renewablesPercentwoBatteries": 27,
  "currentBatteriesStandalone": 441,
  "currentCoal": 0,
  "currentBiogas": 153,
  "currentBatteriesHybrid": 3,
  "currentSmallHydro": 262,
  "AvailableCapacity": 40434,
  "currentHybrids": -8,
  "PS_VERSION": "1.26b",
  "Unloaded_capacity_4H": 17888,
  "renewablesPercent": 27,
  "CurrentNetDemand": 16341,
  "currentBatteries": 434,
  "CurrentNetDemandTS": "20240425051811",
  "OutageDTS": "07/17/2019 23:30:00 (PPT)",
  "currentRenewableswoBatteries": 5670,
  "currentCo2intensity": 0.20939451779330698,
  "TodaysPeakDemand": 21740
}
