{
  "CurrentNetDemandWithoutPumpTS": "20220303094411",
  "slotDate": "03/03/2022 09:45",
  "renewablesPercentwoBatteries": 46,
  "histDemand": "50,270 MW",
  "CurrentSystemDemandWithoutPumpTS": "20220303094411",
  "Available_capacity": 30879,
  "histDemandDate": "Jul 24, 2006",
  "Required_reserve": 1340,
  "CurrentSystemDemandTS": "20220303094456",
  "TodaysPeakDemandTS": "20220303081336",
  "Unloaded_capacity_4H": 12477,
  "Unloaded_capacity_10M": 7239,
  "currentRenewables": 10936,
  "Limitation": "2990.98",
  "PS_VERSION": "1.26b",
  "AvailableCapacity": 39921,
  "renewablesPercent": 46,
  "CurrentAdjustedUnloadedGenerationCapacityTS": "20220303094456",
  "todayForecastPeakDemandTS": "20220303183000",
  "currentCo2intensity": 0.18646845581867058,
  "todayForecastPeakDemand": 27493,
  "currentSolar": 8651,
  "CurrentSystemDemand": 23640,
  "currentCo2": 4408,
  "CurrentAdjustedUnloadedGenerationCapacity": 16281,
  "OutageDTS": "07/17/2019 23:30:00 (PPT)",
  "HistoryFirstDate": "20180410",
  "CurrentNetDemandWithoutPump": 12281,
  "Shutdown": "2501.37",
  "Unloaded_capacity_1H": 11314,
  "Unloaded_capacity_derated_nax": 36502,
  "TodaysPeakDemand": 24524,
  "currentWind": 752,
  "tomorrowsForecastPeakDemand": 26541,
  "CurrentNetDemandTS": "20220303094411",
  "CurrentNetDemand": 13047,
  "currentRenewableswoBatteries": 10791,
  "gridstatus": [
    "Normal"
  ],
  "Current_reserve": 2077,
  "CurrentSystemDemandWithoutPump": 22795
}
