{
  "Unloaded_capacity_derated_max": 29952,
  "todayForecastPeakDemand": 29189,
  "Unloaded_capacity_1H": 11229,
  "Shutdown": "2501.37",
  "currentRenewablesHybrid": null,
  "CurrentSystemDemandWithoutPump": 24217,
  "Required_reserve": 1392,
  "currentCoalCO2": 3,
  "Current_reserve": 1987,
  "currentBiomassCO2": 121,
  "currentOther": 0,
  "HistoryFirstDate": "20180410",
  "currentNuclear": 2260,
  "currentGeothermal": 830,
  "tomorrowsForecastPeakDemand": 28740,
  "Limitation": "2990.98",
  "currentSolar": -32,
  "TodaysPeakDemandTS": "20230227182100",
  "currentImports": 4843,
  "currentNaturalGasCO2": 4826,
  "CurrentAdjustedUnloadedGenerationCapacityTS": "20230227225956",
  "currentBiogasCO2": 106,
  "currentSolarHybrids": -2,
  "Unloaded_capacity_10M": 7166,
  "currentRenewables": 5161,
  "currentWindHybrids": 0,
  "currentCo2": 7246,
  "currentImportsCO2": 2067,
  "CurrentSystemDemandWithoutPumpTS": "20230227225811",
  "Available_capacity": 31689,
  "todayForecastPeakDemandTS": "20230227183000",
  "currentLargeHydro": 2284,
  "CurrentNetDemandWithoutPumpTS": "20230227225811",
  "CurrentNetDemandWithoutPump": 20625,
  "hybridsPercent": 0,
  "currentWind": 3615,
  "currentGeothermalCO2": 7,
  "CurrentSystemDemand": 24523,
  "currentBiomass": 287,
  "currentNonRenewableHybrid": null,
  "CurrentSystemDemandTS": "20230227225956",
  "currentNaturalGas": 11292,
  "histDemand": "50,270 MW",
  "histDemandDate": "Jul 24, 2006",
  "CurrentAdjustedUnloadedGenerationCapacity": 18023,
  "CurrentSystemDemandPlusUnloaded4h": 40515,
  "gridstatus": [
    "Normal"
  ],
  "slotDate": "02/27/2023 23:00",
  "renewablesPercentwoBatteries": 21,
  "currentBatteriesStandalone": 22,
  "currentCoal": 5,
  "currentBiogas": 210,
  "currentBatteriesHybrid": 2,
  "currentSmallHydro": 199,
  "AvailableCapacity": 42546,
  "currentHybrids": 1,
  "PS_VERSION": "1.26b",
  "Unloaded_capacity_4H": 15992,
  "renewablesPercent": 21,
  "CurrentNetDemand": 20979,
  "currentBatteries": -95,
  "CurrentNetDemandTS": "20230227225811",
  "OutageDTS": "07/17/2019 23:30:00 (PPT)",
  "currentRenewableswoBatteries": 5161,
  "currentCo2intensity": 0.29547763042955155,
  "TodaysPeakDemand": 29250
}
