{
  "CurrentNetDemandWithoutPumpTS": "20221031034411",
  "slotDate": "10/31/2022 03:45",
  "renewablesPercentwoBatteries": 9,
  "histDemand": "52,061 MW",
  "CurrentSystemDemandWithoutPumpTS": "20221031034411",
  "Unloaded_capacity_derated_max": 32057,
  "histDemandDate": "Sep 08, 2022",
  "Required_reserve": 1168,
  "CurrentSystemDemandTS": "20221031034456",
  "TodaysPeakDemandTS": "20221031000028",
  "Unloaded_capacity_4H": 16535,
  "Unloaded_capacity_10M": 6790,
  "currentRenewables": 2164,
  "Limitation": "2990.98",
  "PS_VERSION": "1.26b",
  "AvailableCapacity": 39564,
  "renewablesPercent": 11,
  "CurrentAdjustedUnloadedGenerationCapacityTS": "20221031034456",
  "todayForecastPeakDemandTS": "20221031184500",
  "currentCo2intensity": 0.38585004183192234,
  "todayForecastPeakDemand": 28036,
  "currentSolar": -27,
  "CurrentSystemDemand": 20481,
  "currentCo2": 7903,
  "CurrentAdjustedUnloadedGenerationCapacity": 19083,
  "OutageDTS": "07/17/2019 23:30:00 (PPT)",
  "HistoryFirstDate": "20180410",
  "Available_capacity": 27271,
  "CurrentNetDemandWithoutPump": 19103,
  "CurrentSystemDemandPlusUnloaded4h": 37016,
  "Shutdown": "2501.37",
  "Unloaded_capacity_1H": 11446,
  "TodaysPeakDemand": 21759,
  "currentWind": 312,
  "tomorrowsForecastPeakDemand": 27135,
  "CurrentNetDemandTS": "20221031034411",
  "CurrentNetDemand": 20187,
  "currentRenewableswoBatteries": 1843,
  "gridstatus": [
    "Normal"
  ],
  "Current_reserve": 1652,
  "CurrentSystemDemandWithoutPump": 19411
}
