{
  "Unloaded_capacity_derated_max": 34455,
  "todayForecastPeakDemand": 27533,
  "Unloaded_capacity_1H": 9817,
  "Shutdown": "2501.37",
  "currentRenewablesHybrid": null,
  "CurrentSystemDemandWithoutPump": 21664,
  "Required_reserve": 1216,
  "currentCoalCO2": 3,
  "Current_reserve": 1742,
  "currentBiomassCO2": 110,
  "currentOther": 0,
  "HistoryFirstDate": "20180410",
  "currentNuclear": 2263,
  "currentGeothermal": 844,
  "tomorrowsForecastPeakDemand": 26645,
  "Limitation": "2990.98",
  "currentSolar": -15,
  "TodaysPeakDemandTS": "20230623000324",
  "currentImports": 5127,
  "currentNaturalGasCO2": 2776,
  "CurrentAdjustedUnloadedGenerationCapacityTS": "20230623025956",
  "currentBiogasCO2": 119,
  "currentSolarHybrids": -2,
  "Unloaded_capacity_10M": 6551,
  "currentRenewables": 6069,
  "currentWindHybrids": 5,
  "currentCo2": 5288,
  "currentImportsCO2": 2332,
  "CurrentSystemDemandWithoutPumpTS": "20230623025811",
  "Available_capacity": 28739,
  "todayForecastPeakDemandTS": "20230623204500",
  "currentLargeHydro": 4114,
  "CurrentNetDemandWithoutPumpTS": "20230623025811",
  "CurrentNetDemandWithoutPump": 17270,
  "hybridsPercent": 0.1,
  "currentWind": 4433,
  "currentGeothermalCO2": 8,
  "CurrentSystemDemand": 22188,
  "currentBiomass": 248,
  "currentNonRenewableHybrid": null,
  "CurrentSystemDemandTS": "20230623025956",
  "currentNaturalGas": 6055,
  "histDemand": "52,061 MW",
  "histDemandDate": "Sep 6, 2022",
  "CurrentAdjustedUnloadedGenerationCapacity": 16533,
  "CurrentSystemDemandPlusUnloaded4h": 37928,
  "gridstatus": [
    "Normal"
  ],
  "slotDate": "06/23/2023 03:00",
  "renewablesPercentwoBatteries": 27,
  "currentBatteriesStandalone": -666,
  "currentCoal": 4,
  "currentBiogas": 225,
  "currentBatteriesHybrid": 14,
  "currentSmallHydro": 365,
  "AvailableCapacity": 38721,
  "currentHybrids": 13,
  "PS_VERSION": "1.26b",
  "Unloaded_capacity_4H": 15740,
  "renewablesPercent": 27,
  "CurrentNetDemand": 17940,
  "currentBatteries": -868,
  "CurrentNetDemandTS": "20230623025811",
  "OutageDTS": "07/17/2019 23:30:00 (PPT)",
  "currentRenewableswoBatteries": 6069,
  "currentCo2intensity": 0.238337613367081,
  "TodaysPeakDemand": 23899
}
