{
  "Unloaded_capacity_derated_max": 27119,
  "todayForecastPeakDemand": 30294,
  "Unloaded_capacity_1H": 10134,
  "Shutdown": "2501.37",
  "currentRenewablesHybrid": null,
  "CurrentSystemDemandWithoutPump": 30231,
  "Required_reserve": 1659,
  "currentCoalCO2": 0,
  "Current_reserve": 2328,
  "currentBiomassCO2": 156,
  "currentOther": 0,
  "HistoryFirstDate": "20180410",
  "currentNuclear": 2217,
  "currentGeothermal": 832,
  "tomorrowsForecastPeakDemand": 28429,
  "Limitation": "2990.98",
  "currentSolar": 0,
  "TodaysPeakDemandTS": "20230902194804",
  "currentImports": 7051,
  "currentNaturalGasCO2": 5215,
  "CurrentAdjustedUnloadedGenerationCapacityTS": "20230902195956",
  "currentBiogasCO2": 113,
  "currentSolarHybrids": -4,
  "Unloaded_capacity_10M": 6043,
  "currentRenewables": 3424,
  "currentWindHybrids": 0,
  "currentCo2": 8572,
  "currentImportsCO2": 3074,
  "CurrentSystemDemandWithoutPumpTS": "20230902195811",
  "Available_capacity": 36270,
  "todayForecastPeakDemandTS": "20230902193000",
  "currentLargeHydro": 4775,
  "CurrentNetDemandWithoutPumpTS": "20230902195811",
  "CurrentNetDemandWithoutPump": 28617,
  "hybridsPercent": 0.9,
  "currentWind": 1698,
  "currentGeothermalCO2": 8,
  "CurrentSystemDemand": 30226,
  "currentBiomass": 362,
  "currentNonRenewableHybrid": null,
  "CurrentSystemDemandTS": "20230902195956",
  "currentNaturalGas": 12036,
  "histDemand": "52,061 MW",
  "histDemandDate": "Sep 6, 2022",
  "CurrentAdjustedUnloadedGenerationCapacity": 16678,
  "CurrentSystemDemandPlusUnloaded4h": 46573,
  "gridstatus": [
    "Normal"
  ],
  "slotDate": "09/02/2023 20:00",
  "renewablesPercentwoBatteries": 11,
  "currentBatteriesStandalone": 1663,
  "currentCoal": 0,
  "currentBiogas": 220,
  "currentBatteriesHybrid": 242,
  "currentSmallHydro": 356,
  "AvailableCapacity": 46904,
  "currentHybrids": 254,
  "PS_VERSION": "1.26b",
  "Unloaded_capacity_4H": 16347,
  "renewablesPercent": 11,
  "CurrentNetDemand": 28581,
  "currentBatteries": 1753,
  "CurrentNetDemandTS": "20230902195811",
  "OutageDTS": "07/17/2019 23:30:00 (PPT)",
  "currentRenewableswoBatteries": 3424,
  "currentCo2intensity": 0.28357693891983476,
  "TodaysPeakDemand": 30360
}
