{
  "Unloaded_capacity_derated_max": 32107,
  "todayForecastPeakDemand": 25168,
  "Unloaded_capacity_1H": 8695,
  "Shutdown": "2501.37",
  "currentRenewablesHybrid": null,
  "CurrentSystemDemandWithoutPump": 19181,
  "Required_reserve": 1188,
  "currentCoalCO2": 3,
  "Current_reserve": 1570,
  "currentBiomassCO2": 51,
  "currentOther": 0,
  "HistoryFirstDate": "20180410",
  "currentNuclear": 2276,
  "currentGeothermal": 961,
  "tomorrowsForecastPeakDemand": 26837,
  "Limitation": "2990.98",
  "currentSolar": 444,
  "TodaysPeakDemandTS": "20230423000144",
  "currentImports": 1450,
  "currentNaturalGasCO2": 3072,
  "CurrentAdjustedUnloadedGenerationCapacityTS": "20230423062956",
  "currentBiogasCO2": 112,
  "currentSolarHybrids": 25,
  "Unloaded_capacity_10M": 5217,
  "currentRenewables": 4918,
  "currentWindHybrids": 28,
  "currentCo2": 4029,
  "currentImportsCO2": 712,
  "CurrentSystemDemandWithoutPumpTS": "20230423062811",
  "Available_capacity": 24488,
  "todayForecastPeakDemandTS": "20230423204500",
  "currentLargeHydro": 3690,
  "CurrentNetDemandWithoutPumpTS": "20230423062811",
  "CurrentNetDemandWithoutPump": 15894,
  "hybridsPercent": 0.3,
  "currentWind": 2977,
  "currentGeothermalCO2": 9,
  "CurrentSystemDemand": 19271,
  "currentBiomass": 112,
  "currentNonRenewableHybrid": null,
  "CurrentSystemDemandTS": "20230423062956",
  "currentNaturalGas": 6710,
  "histDemand": "52,061 MW",
  "histDemandDate": "Sep 6, 2022",
  "CurrentAdjustedUnloadedGenerationCapacity": 15873,
  "CurrentSystemDemandPlusUnloaded4h": 32174,
  "gridstatus": [
    "Normal"
  ],
  "slotDate": "04/23/2023 06:30",
  "renewablesPercentwoBatteries": 26,
  "currentBatteriesStandalone": 293,
  "currentCoal": 3,
  "currentBiogas": 206,
  "currentBatteriesHybrid": 13,
  "currentSmallHydro": 361,
  "AvailableCapacity": 35144,
  "currentHybrids": 66,
  "PS_VERSION": "1.26b",
  "Unloaded_capacity_4H": 12903,
  "renewablesPercent": 26,
  "CurrentNetDemand": 15975,
  "currentBatteries": 339,
  "CurrentNetDemandTS": "20230423062811",
  "OutageDTS": "07/17/2019 23:30:00 (PPT)",
  "currentRenewableswoBatteries": 4918,
  "currentCo2intensity": 0.20905193401127142,
  "TodaysPeakDemand": 21894
}
