{
  "Unloaded_capacity_derated_max": 32742,
  "todayForecastPeakDemand": 28714,
  "Unloaded_capacity_1H": 12436,
  "Shutdown": "2501.37",
  "currentRenewablesHybrid": null,
  "CurrentSystemDemandWithoutPump": 22002,
  "Required_reserve": 1218,
  "currentCoalCO2": 0,
  "Current_reserve": 1769,
  "currentBiomassCO2": 98,
  "currentOther": 0,
  "HistoryFirstDate": "20180410",
  "currentNuclear": 1105,
  "currentGeothermal": 765,
  "tomorrowsForecastPeakDemand": 27875,
  "Limitation": "2990.98",
  "currentSolar": -53,
  "TodaysPeakDemandTS": "20231024001620",
  "currentImports": 4902,
  "currentNaturalGasCO2": 4947,
  "CurrentAdjustedUnloadedGenerationCapacityTS": "20231024054956",
  "currentBiogasCO2": 87,
  "currentSolarHybrids": -3,
  "Unloaded_capacity_10M": 7874,
  "currentRenewables": 2987,
  "currentWindHybrids": 0,
  "currentCo2": 7327,
  "currentImportsCO2": 2219,
  "CurrentSystemDemandWithoutPumpTS": "20231024054811",
  "Available_capacity": 29928,
  "todayForecastPeakDemandTS": "20231024184500",
  "currentLargeHydro": 1766,
  "CurrentNetDemandWithoutPumpTS": "20231024054811",
  "CurrentNetDemandWithoutPump": 20371,
  "hybridsPercent": 0.2,
  "currentWind": 1612,
  "currentGeothermalCO2": 7,
  "CurrentSystemDemand": 22054,
  "currentBiomass": 220,
  "currentNonRenewableHybrid": null,
  "CurrentSystemDemandTS": "20231024054956",
  "currentNaturalGas": 11223,
  "histDemand": "52,061 MW",
  "histDemandDate": "Sep 6, 2022",
  "CurrentAdjustedUnloadedGenerationCapacity": 20710,
  "CurrentSystemDemandPlusUnloaded4h": 42188,
  "gridstatus": [
    "Normal"
  ],
  "slotDate": "10/24/2023 05:50",
  "renewablesPercentwoBatteries": 14,
  "currentBatteriesStandalone": 674,
  "currentCoal": 0,
  "currentBiogas": 165,
  "currentBatteriesHybrid": 49,
  "currentSmallHydro": 207,
  "AvailableCapacity": 42764,
  "currentHybrids": 44,
  "PS_VERSION": "1.26b",
  "Unloaded_capacity_4H": 20134,
  "renewablesPercent": 14,
  "CurrentNetDemand": 20437,
  "currentBatteries": 615,
  "CurrentNetDemandTS": "20231024054811",
  "OutageDTS": "07/17/2019 23:30:00 (PPT)",
  "currentRenewableswoBatteries": 2987,
  "currentCo2intensity": 0.3322526853348903,
  "TodaysPeakDemand": 22996
}
