{
  "Unloaded_capacity_derated_max": 34438,
  "todayForecastPeakDemand": 26293,
  "Unloaded_capacity_1H": 9749,
  "Shutdown": "2501.37",
  "currentRenewablesHybrid": null,
  "CurrentSystemDemandWithoutPump": 21085,
  "Required_reserve": 1198,
  "currentCoalCO2": 3,
  "Current_reserve": 1484,
  "currentBiomassCO2": 127,
  "currentOther": 0,
  "HistoryFirstDate": "20180410",
  "currentNuclear": 2258,
  "currentGeothermal": 748,
  "tomorrowsForecastPeakDemand": 26186,
  "Limitation": "2990.98",
  "currentSolar": 2449,
  "TodaysPeakDemandTS": "20230610000128",
  "currentImports": 3953,
  "currentNaturalGasCO2": 2474,
  "CurrentAdjustedUnloadedGenerationCapacityTS": "20230610064456",
  "currentBiogasCO2": 109,
  "currentSolarHybrids": 88,
  "Unloaded_capacity_10M": 6227,
  "currentRenewables": 6854,
  "currentWindHybrids": 6,
  "currentCo2": 4775,
  "currentImportsCO2": 1812,
  "CurrentSystemDemandWithoutPumpTS": "20230610064411",
  "Available_capacity": 27419,
  "todayForecastPeakDemandTS": "20230610211500",
  "currentLargeHydro": 3220,
  "CurrentNetDemandWithoutPumpTS": "20230610064411",
  "CurrentNetDemandWithoutPump": 15899,
  "hybridsPercent": 0.7,
  "currentWind": 2936,
  "currentGeothermalCO2": 7,
  "CurrentSystemDemand": 21192,
  "currentBiomass": 281,
  "currentNonRenewableHybrid": null,
  "CurrentSystemDemandTS": "20230610064456",
  "currentNaturalGas": 5293,
  "histDemand": "52,061 MW",
  "histDemandDate": "Sep 6, 2022",
  "CurrentAdjustedUnloadedGenerationCapacity": 18765,
  "CurrentSystemDemandPlusUnloaded4h": 36908,
  "gridstatus": [
    "Normal"
  ],
  "slotDate": "06/10/2023 06:45",
  "renewablesPercentwoBatteries": 32,
  "currentBatteriesStandalone": 228,
  "currentCoal": 3,
  "currentBiogas": 203,
  "currentBatteriesHybrid": 49,
  "currentSmallHydro": 364,
  "AvailableCapacity": 39957,
  "currentHybrids": 142,
  "PS_VERSION": "1.26b",
  "Unloaded_capacity_4H": 15716,
  "renewablesPercent": 32,
  "CurrentNetDemand": 15957,
  "currentBatteries": 272,
  "CurrentNetDemandTS": "20230610064411",
  "OutageDTS": "07/17/2019 23:30:00 (PPT)",
  "currentRenewableswoBatteries": 6854,
  "currentCo2intensity": 0.22532087127284786,
  "TodaysPeakDemand": 23847
}
