{
  "CurrentNetDemandWithoutPumpTS": "20220315005811",
  "slotDate": "03/15/2022 01:00",
  "renewablesPercentwoBatteries": 17,
  "histDemand": "50,270 MW",
  "CurrentSystemDemandWithoutPumpTS": "20220315005811",
  "Available_capacity": 27129,
  "histDemandDate": "Jul 24, 2006",
  "Required_reserve": 1399,
  "CurrentSystemDemandTS": "20220315005956",
  "TodaysPeakDemandTS": "20220315000124",
  "Unloaded_capacity_4H": 10945,
  "Unloaded_capacity_10M": 6322,
  "currentRenewables": 3533,
  "Limitation": "2990.98",
  "PS_VERSION": "1.26b",
  "AvailableCapacity": 35909,
  "renewablesPercent": 17,
  "CurrentAdjustedUnloadedGenerationCapacityTS": "20220315005956",
  "todayForecastPeakDemandTS": "20220315194500",
  "currentCo2intensity": 0.29581616126648413,
  "todayForecastPeakDemand": 26784,
  "currentSolar": -42,
  "CurrentSystemDemand": 20807,
  "currentCo2": 6155,
  "CurrentAdjustedUnloadedGenerationCapacity": 15102,
  "OutageDTS": "07/17/2019 23:30:00 (PPT)",
  "HistoryFirstDate": "20180410",
  "CurrentNetDemandWithoutPump": 18777,
  "Shutdown": "2501.37",
  "Unloaded_capacity_1H": 10103,
  "Unloaded_capacity_derated_nax": 33512,
  "TodaysPeakDemand": 21702,
  "currentWind": 2098,
  "tomorrowsForecastPeakDemand": 26561,
  "CurrentNetDemandTS": "20220315005811",
  "CurrentNetDemand": 18800,
  "currentRenewableswoBatteries": 3623,
  "gridstatus": [
    "Normal"
  ],
  "Current_reserve": 2128,
  "CurrentSystemDemandWithoutPump": 20720
}
