{
  "CurrentNetDemandWithoutPumpTS": "20220511105811",
  "slotDate": "05/11/2022 11:00",
  "renewablesPercentwoBatteries": 69,
  "histDemand": "50,270 MW",
  "CurrentSystemDemandWithoutPumpTS": "20220511105811",
  "Available_capacity": 27795,
  "histDemandDate": "Jul 24, 2006",
  "Required_reserve": 1229,
  "CurrentSystemDemandTS": "20220511105956",
  "TodaysPeakDemandTS": "20220511075828",
  "Unloaded_capacity_4H": 11617,
  "Unloaded_capacity_10M": 7472,
  "currentRenewables": 14452,
  "Limitation": "2990.98",
  "PS_VERSION": "1.26b",
  "AvailableCapacity": 37186,
  "renewablesPercent": 71,
  "CurrentAdjustedUnloadedGenerationCapacityTS": "20220511105956",
  "todayForecastPeakDemandTS": "20220511203000",
  "currentCo2intensity": 0.1340538349722169,
  "todayForecastPeakDemand": 26077,
  "currentSolar": 8822,
  "CurrentSystemDemand": 20323,
  "currentCo2": 2724,
  "CurrentAdjustedUnloadedGenerationCapacity": 16863,
  "OutageDTS": "07/17/2019 23:30:00 (PPT)",
  "HistoryFirstDate": "20180410",
  "CurrentNetDemandWithoutPump": 6627,
  "Shutdown": "2501.37",
  "Unloaded_capacity_1H": 10589,
  "Unloaded_capacity_derated_nax": 39023,
  "TodaysPeakDemand": 24203,
  "currentWind": 3859,
  "tomorrowsForecastPeakDemand": 26387,
  "CurrentNetDemandTS": "20220511105811",
  "CurrentNetDemand": 7569,
  "currentRenewableswoBatteries": 14107,
  "gridstatus": [
    "Normal"
  ],
  "Current_reserve": 2564,
  "CurrentSystemDemandWithoutPump": 19500
}
