{
  "Unloaded_capacity_derated_max": 38423,
  "todayForecastPeakDemand": 25292,
  "Unloaded_capacity_1H": 9818,
  "Shutdown": "2501.37",
  "currentRenewablesHybrid": null,
  "CurrentSystemDemandWithoutPump": 19188,
  "Required_reserve": 1194,
  "currentCoalCO2": 0,
  "Current_reserve": 1817,
  "currentBiomassCO2": 138,
  "currentOther": 0,
  "HistoryFirstDate": "20180410",
  "currentNuclear": 2271,
  "currentGeothermal": 727,
  "tomorrowsForecastPeakDemand": 25066,
  "Limitation": "2990.98",
  "currentSolar": 88,
  "TodaysPeakDemandTS": "20240326000232",
  "currentImports": 5811,
  "currentNaturalGasCO2": 880,
  "CurrentAdjustedUnloadedGenerationCapacityTS": "20240326025956",
  "currentBiogasCO2": 95,
  "currentSolarHybrids": -3,
  "Unloaded_capacity_10M": 6713,
  "currentRenewables": 6681,
  "currentWindHybrids": 0,
  "currentCo2": 3869,
  "currentImportsCO2": 2737,
  "CurrentSystemDemandWithoutPumpTS": "20240326025811",
  "Available_capacity": 26755,
  "todayForecastPeakDemandTS": "20240326201500",
  "currentLargeHydro": 3291,
  "CurrentNetDemandWithoutPumpTS": "20240326025811",
  "CurrentNetDemandWithoutPump": 13978,
  "hybridsPercent": 0,
  "currentWind": 5160,
  "currentGeothermalCO2": 7,
  "CurrentSystemDemand": 20043,
  "currentBiomass": 294,
  "currentNonRenewableHybrid": null,
  "CurrentSystemDemandTS": "20240326025956",
  "currentNaturalGas": 1930,
  "histDemand": "52,061 MW",
  "histDemandDate": "Sep 6, 2022",
  "CurrentAdjustedUnloadedGenerationCapacity": 19600,
  "CurrentSystemDemandPlusUnloaded4h": 38446,
  "gridstatus": [
    "Normal"
  ],
  "slotDate": "03/26/2024 03:00",
  "renewablesPercentwoBatteries": 33,
  "currentBatteriesStandalone": -453,
  "currentCoal": 0,
  "currentBiogas": 170,
  "currentBatteriesHybrid": -6,
  "currentSmallHydro": 265,
  "AvailableCapacity": 39643,
  "currentHybrids": -8,
  "PS_VERSION": "1.26b",
  "Unloaded_capacity_4H": 18403,
  "renewablesPercent": 33,
  "CurrentNetDemand": 14761,
  "currentBatteries": -410,
  "CurrentNetDemandTS": "20240326025811",
  "OutageDTS": "07/17/2019 23:30:00 (PPT)",
  "currentRenewableswoBatteries": 6681,
  "currentCo2intensity": 0.1930296775919014,
  "TodaysPeakDemand": 21313
}
