{
  "Unloaded_capacity_derated_max": 28978,
  "todayForecastPeakDemand": 40695,
  "Unloaded_capacity_1H": 11875,
  "Shutdown": "2501.37",
  "currentRenewablesHybrid": null,
  "CurrentSystemDemandWithoutPump": 24074,
  "Required_reserve": 1403,
  "currentCoalCO2": 1,
  "Current_reserve": 1780,
  "currentBiomassCO2": 150,
  "currentOther": 0,
  "HistoryFirstDate": "20180410",
  "currentNuclear": 2265,
  "currentGeothermal": 822,
  "tomorrowsForecastPeakDemand": 41451,
  "Limitation": "2990.98",
  "currentSolar": 1741,
  "TodaysPeakDemandTS": "20230715000044",
  "currentImports": 3546,
  "currentNaturalGasCO2": 5170,
  "CurrentAdjustedUnloadedGenerationCapacityTS": "20230715062956",
  "currentBiogasCO2": 119,
  "currentSolarHybrids": 119,
  "Unloaded_capacity_10M": 7124,
  "currentRenewables": 5036,
  "currentWindHybrids": 0,
  "currentCo2": 7236,
  "currentImportsCO2": 1615,
  "CurrentSystemDemandWithoutPumpTS": "20230715062811",
  "Available_capacity": 31412,
  "todayForecastPeakDemandTS": "20230715184500",
  "currentLargeHydro": 2617,
  "CurrentNetDemandWithoutPumpTS": "20230715062811",
  "CurrentNetDemandWithoutPump": 20846,
  "hybridsPercent": 0.4,
  "currentWind": 1770,
  "currentGeothermalCO2": 8,
  "CurrentSystemDemand": 24288,
  "currentBiomass": 336,
  "currentNonRenewableHybrid": null,
  "CurrentSystemDemandTS": "20230715062956",
  "currentNaturalGas": 11441,
  "histDemand": "52,061 MW",
  "histDemandDate": "Sep 6, 2022",
  "CurrentAdjustedUnloadedGenerationCapacity": 21893,
  "CurrentSystemDemandPlusUnloaded4h": 42198,
  "gridstatus": [
    "Normal"
  ],
  "slotDate": "07/15/2023 06:30",
  "renewablesPercentwoBatteries": 21,
  "currentBatteriesStandalone": 41,
  "currentCoal": 2,
  "currentBiogas": 226,
  "currentBatteriesHybrid": -23,
  "currentSmallHydro": 422,
  "AvailableCapacity": 46181,
  "currentHybrids": 114,
  "PS_VERSION": "1.26b",
  "Unloaded_capacity_4H": 17910,
  "renewablesPercent": 21,
  "CurrentNetDemand": 21049,
  "currentBatteries": 58,
  "CurrentNetDemandTS": "20230715062811",
  "OutageDTS": "07/17/2019 23:30:00 (PPT)",
  "currentRenewableswoBatteries": 5036,
  "currentCo2intensity": 0.2979396736248005,
  "TodaysPeakDemand": 30549
}
