{
  "todayForecastPeakDemandTS": "20210503203000",
  "AvailableCapacity": 36250,
  "currentWind": 3961,
  "Limitation": 0,
  "CurrentSystemDemandWithoutPump": 19697,
  "histDemand": "50,270 MW",
  "TodaysPeakDemand": 21035,
  "slotDate": "05/03/2021 01:45",
  "gridstatus": [
    "Normal"
  ],
  "currentCo2intensity": 0.2648510510773653,
  "CurrentNetDemandWithoutPump": 15871,
  "histDemandDate": "Jul 24, 2006",
  "CurrentNetDemand": 15808,
  "CurrentSystemDemand": 19709,
  "Shutdown": 0,
  "HistoryFirstDate": "20180410",
  "CurrentAdjustedUnloadedGenerationCapacityTS": "20210503014456",
  "CurrentSystemDemandWithoutPumpTS": "20210503014411",
  "currentRenewableswoBatteries": 5545,
  "TodaysPeakDemandTS": "20210503000316",
  "currentRenewables": 5660,
  "CurrentNetDemandTS": "20210503014411",
  "CurrentAdjustedUnloadedGenerationCapacity": 16541,
  "renewablesPercent": 29,
  "CurrentNetDemandWithoutPumpTS": "20210503014411",
  "tomorrowsForecastPeakDemand": 29420,
  "PS_VERSION": "1.26b",
  "CurrentSystemDemandTS": null,
  "currentSolar": -36,
  "renewablesPercentwoBatteries": 28,
  "OutageDTS": null,
  "currentCo2": 5220,
  "todayForecastPeakDemand": 28723
}
