{
  "Unloaded_capacity_derated_max": 30642,
  "todayForecastPeakDemand": 24910,
  "Unloaded_capacity_1H": 7603,
  "Shutdown": "2501.37",
  "currentRenewablesHybrid": null,
  "CurrentSystemDemandWithoutPump": 24047,
  "Required_reserve": 1367,
  "currentCoalCO2": 2,
  "Current_reserve": 1921,
  "currentBiomassCO2": 100,
  "currentOther": 0,
  "HistoryFirstDate": "20180410",
  "currentNuclear": 1627,
  "currentGeothermal": 911,
  "tomorrowsForecastPeakDemand": 26279,
  "Limitation": "2990.98",
  "currentSolar": 26,
  "TodaysPeakDemandTS": "20230319193648",
  "currentImports": 5164,
  "currentNaturalGasCO2": 3700,
  "CurrentAdjustedUnloadedGenerationCapacityTS": "20230319205956",
  "currentBiogasCO2": 108,
  "currentSolarHybrids": -3,
  "Unloaded_capacity_10M": 4507,
  "currentRenewables": 4764,
  "currentWindHybrids": 0,
  "currentCo2": 6185,
  "currentImportsCO2": 2158,
  "CurrentSystemDemandWithoutPumpTS": "20230319205811",
  "Available_capacity": 28864,
  "todayForecastPeakDemandTS": "20230319194500",
  "currentLargeHydro": 3602,
  "CurrentNetDemandWithoutPumpTS": "20230319205811",
  "CurrentNetDemandWithoutPump": 20935,
  "hybridsPercent": 0.6,
  "currentWind": 3017,
  "currentGeothermalCO2": 8,
  "CurrentSystemDemand": 24357,
  "currentBiomass": 242,
  "currentNonRenewableHybrid": null,
  "CurrentSystemDemandTS": "20230319205956",
  "currentNaturalGas": 9080,
  "histDemand": "50,270 MW",
  "histDemandDate": "Jul 24, 2006",
  "CurrentAdjustedUnloadedGenerationCapacity": 14147,
  "CurrentSystemDemandPlusUnloaded4h": 36099,
  "gridstatus": [
    "Normal"
  ],
  "slotDate": "03/19/2023 21:00",
  "renewablesPercentwoBatteries": 20,
  "currentBatteriesStandalone": 1155,
  "currentCoal": 2,
  "currentBiogas": 221,
  "currentBatteriesHybrid": 70,
  "currentSmallHydro": 255,
  "AvailableCapacity": 38504,
  "currentHybrids": 116,
  "PS_VERSION": "1.26b",
  "Unloaded_capacity_4H": 11742,
  "renewablesPercent": 20,
  "CurrentNetDemand": 21298,
  "currentBatteries": 1044,
  "CurrentNetDemandTS": "20230319205811",
  "OutageDTS": "07/17/2019 23:30:00 (PPT)",
  "currentRenewableswoBatteries": 4764,
  "currentCo2intensity": 0.25395259481672794,
  "TodaysPeakDemand": 24999
}
