{
  "Unloaded_capacity_derated_max": 29632,
  "todayForecastPeakDemand": 27376,
  "Unloaded_capacity_1H": 9376,
  "Shutdown": "2501.37",
  "currentRenewablesHybrid": null,
  "CurrentSystemDemandWithoutPump": 24669,
  "Required_reserve": 1414,
  "currentCoalCO2": -1,
  "Current_reserve": 1563,
  "currentBiomassCO2": 77,
  "currentOther": 0,
  "HistoryFirstDate": "20180410",
  "currentNuclear": 2261,
  "currentGeothermal": 793,
  "tomorrowsForecastPeakDemand": 26881,
  "Limitation": "2990.98",
  "currentSolar": -54,
  "TodaysPeakDemandTS": "20241205090200",
  "currentImports": 4600,
  "currentNaturalGasCO2": 5238,
  "CurrentAdjustedUnloadedGenerationCapacityTS": "20241205221456",
  "currentBiogasCO2": 92,
  "currentSolarHybrids": -2,
  "Unloaded_capacity_10M": 6592,
  "currentRenewables": 1919,
  "currentWindHybrids": 0,
  "currentCo2": 7512,
  "currentImportsCO2": 2065,
  "CurrentSystemDemandWithoutPumpTS": "20241205221411",
  "Available_capacity": 31643,
  "todayForecastPeakDemandTS": "20241205174500",
  "currentLargeHydro": 1707,
  "CurrentNetDemandWithoutPumpTS": "20241205221411",
  "CurrentNetDemandWithoutPump": 24120,
  "hybridsPercent": 0.8,
  "currentWind": 676,
  "currentGeothermalCO2": 7,
  "CurrentSystemDemand": 25052,
  "currentBiomass": 173,
  "currentNonRenewableHybrid": null,
  "CurrentSystemDemandTS": "20241205221456",
  "currentNaturalGas": 11826,
  "histDemand": "52,061 MW",
  "histDemandDate": "Sep 6, 2022",
  "CurrentAdjustedUnloadedGenerationCapacity": 21237,
  "CurrentSystemDemandPlusUnloaded4h": 42263,
  "gridstatus": [
    "Normal"
  ],
  "slotDate": "12/05/2024 22:15",
  "renewablesPercentwoBatteries": 8,
  "currentBatteriesStandalone": 1891,
  "currentCoal": -1,
  "currentBiogas": 175,
  "currentBatteriesHybrid": 204,
  "currentSmallHydro": 144,
  "AvailableCapacity": 46289,
  "currentHybrids": 216,
  "PS_VERSION": "1.26b",
  "Unloaded_capacity_4H": 17211,
  "renewablesPercent": 8,
  "CurrentNetDemand": 24437,
  "currentBatteries": 2117,
  "CurrentNetDemandTS": "20241205221411",
  "OutageDTS": "07/17/2019 23:30:00 (PPT)",
  "currentRenewableswoBatteries": 1919,
  "currentCo2intensity": 0.2998704744911612,
  "TodaysPeakDemand": 28303
}
