{
  "CurrentNetDemandWithoutPumpTS": "20220106155811",
  "slotDate": "01/06/2022 16:00",
  "renewablesPercentwoBatteries": 26,
  "histDemand": "50,270 MW",
  "CurrentSystemDemandWithoutPumpTS": "20220106155811",
  "Available_capacity": 32472,
  "histDemandDate": "Jul 24, 2006",
  "Required_reserve": 1337,
  "CurrentSystemDemandTS": "20220106160000",
  "TodaysPeakDemandTS": "20220106074336",
  "Unloaded_capacity_4H": 14149,
  "Unloaded_capacity_10M": 7312,
  "currentRenewables": 6381,
  "Limitation": "2990.98",
  "PS_VERSION": "1.26b",
  "AvailableCapacity": 42181,
  "renewablesPercent": 25,
  "CurrentAdjustedUnloadedGenerationCapacityTS": "20220106160000",
  "todayForecastPeakDemandTS": "20220106174500",
  "currentCo2intensity": 0.274080656806509,
  "todayForecastPeakDemand": 28370,
  "currentSolar": 4169,
  "CurrentSystemDemand": 25160,
  "currentCo2": 6896,
  "CurrentAdjustedUnloadedGenerationCapacity": 17021,
  "OutageDTS": "07/17/2019 23:30:00 (PPT)",
  "HistoryFirstDate": "20180410",
  "CurrentNetDemandWithoutPump": 20464,
  "Shutdown": "2501.37",
  "Unloaded_capacity_1H": 12495,
  "Unloaded_capacity_derated_nax": 32542,
  "TodaysPeakDemand": 26197,
  "currentWind": 803,
  "tomorrowsForecastPeakDemand": 27736,
  "CurrentNetDemandTS": "20220106155811",
  "CurrentNetDemand": 20783,
  "currentRenewableswoBatteries": 6555,
  "gridstatus": [
    "Normal"
  ],
  "Current_reserve": 1916,
  "CurrentSystemDemandWithoutPump": 25033
}
