{
  "todayForecastPeakDemandTS": "20210709174500",
  "AvailableCapacity": 49790,
  "currentWind": 599,
  "Limitation": 0,
  "CurrentSystemDemandWithoutPump": 31143,
  "histDemand": "50,270 MW",
  "TodaysPeakDemand": 31521,
  "slotDate": "07/09/2021 09:40",
  "gridstatus": [
    "Normal"
  ],
  "currentCo2intensity": 0.22792596508607924,
  "CurrentNetDemandWithoutPump": 19670,
  "histDemandDate": "Jul 24, 2006",
  "CurrentNetDemand": 20013,
  "CurrentSystemDemand": 31520,
  "Shutdown": 0,
  "HistoryFirstDate": "20180410",
  "CurrentAdjustedUnloadedGenerationCapacityTS": "20210709093956",
  "CurrentSystemDemandWithoutPumpTS": "20210709093811",
  "currentRenewableswoBatteries": 13108,
  "TodaysPeakDemandTS": "20210709093932",
  "currentRenewables": 13393,
  "CurrentNetDemandTS": "20210709093811",
  "CurrentAdjustedUnloadedGenerationCapacity": 18270,
  "renewablesPercent": 42,
  "CurrentNetDemandWithoutPumpTS": "20210709093811",
  "tomorrowsForecastPeakDemand": 40627,
  "PS_VERSION": "1.26b",
  "CurrentSystemDemandTS": null,
  "currentSolar": 10814,
  "renewablesPercentwoBatteries": 42,
  "OutageDTS": null,
  "currentCo2": 7184,
  "todayForecastPeakDemand": 42910
}
