{
  "Unloaded_capacity_derated_max": 35050,
  "todayForecastPeakDemand": 25970,
  "Unloaded_capacity_1H": 9074,
  "Shutdown": "2501.37",
  "currentRenewablesHybrid": null,
  "CurrentSystemDemandWithoutPump": 22972,
  "Required_reserve": 1615,
  "currentCoalCO2": 3,
  "Current_reserve": 2300,
  "currentBiomassCO2": 57,
  "currentOther": 0,
  "HistoryFirstDate": "20180410",
  "currentNuclear": 2278,
  "currentGeothermal": 999,
  "tomorrowsForecastPeakDemand": 26263,
  "Limitation": "2990.98",
  "currentSolar": 12409,
  "TodaysPeakDemandTS": "20230417090700",
  "currentImports": -2768,
  "currentNaturalGasCO2": 2667,
  "CurrentAdjustedUnloadedGenerationCapacityTS": "20230417094456",
  "currentBiogasCO2": 113,
  "currentSolarHybrids": 742,
  "Unloaded_capacity_10M": 5414,
  "currentRenewables": 18893,
  "currentWindHybrids": 25,
  "currentCo2": 1709,
  "currentImportsCO2": -1106,
  "CurrentSystemDemandWithoutPumpTS": "20230417094411",
  "Available_capacity": 30092,
  "todayForecastPeakDemandTS": "20230417203000",
  "currentLargeHydro": 2495,
  "CurrentNetDemandWithoutPumpTS": "20230417094411",
  "CurrentNetDemandWithoutPump": 6612,
  "hybridsPercent": 2.7,
  "currentWind": 4870,
  "currentGeothermalCO2": 9,
  "CurrentSystemDemand": 24678,
  "currentBiomass": 132,
  "currentNonRenewableHybrid": null,
  "CurrentSystemDemandTS": "20230417094456",
  "currentNaturalGas": 6111,
  "histDemand": "52,061 MW",
  "histDemandDate": "Sep 6, 2022",
  "CurrentAdjustedUnloadedGenerationCapacity": 14720,
  "CurrentSystemDemandPlusUnloaded4h": 38272,
  "gridstatus": [
    "Normal"
  ],
  "slotDate": "04/17/2023 09:45",
  "renewablesPercentwoBatteries": 77,
  "currentBatteriesStandalone": -309,
  "currentCoal": 3,
  "currentBiogas": 219,
  "currentBatteriesHybrid": -111,
  "currentSmallHydro": 323,
  "AvailableCapacity": 39398,
  "currentHybrids": 659,
  "PS_VERSION": "1.26b",
  "Unloaded_capacity_4H": 13594,
  "renewablesPercent": 77,
  "CurrentNetDemand": 8202,
  "currentBatteries": -413,
  "CurrentNetDemandTS": "20230417094411",
  "OutageDTS": "07/17/2019 23:30:00 (PPT)",
  "currentRenewableswoBatteries": 18893,
  "currentCo2intensity": 0.06927328301922055,
  "TodaysPeakDemand": 25055
}
