{
  "todayForecastPeakDemandTS": "20210413200000",
  "AvailableCapacity": 38542,
  "currentWind": 4469,
  "Limitation": 0,
  "CurrentSystemDemandWithoutPump": 25320,
  "histDemand": "50,270 MW",
  "TodaysPeakDemand": 25363,
  "slotDate": "04/13/2021 18:50",
  "gridstatus": [
    "Normal"
  ],
  "currentCo2intensity": 0.27177940677803214,
  "CurrentNetDemandWithoutPump": 19662,
  "histDemandDate": "Jul 24, 2006",
  "CurrentNetDemand": 19706,
  "CurrentSystemDemand": 25363,
  "Shutdown": 0,
  "HistoryFirstDate": "20180410",
  "CurrentAdjustedUnloadedGenerationCapacityTS": "20210413184956",
  "CurrentSystemDemandWithoutPumpTS": "20210413184811",
  "currentRenewableswoBatteries": 7226,
  "TodaysPeakDemandTS": "20210413184956",
  "currentRenewables": 7109,
  "CurrentNetDemandTS": "20210413184811",
  "CurrentAdjustedUnloadedGenerationCapacity": 13179,
  "renewablesPercent": 28,
  "CurrentNetDemandWithoutPumpTS": "20210413184811",
  "tomorrowsForecastPeakDemand": 26028,
  "PS_VERSION": "1.26b",
  "CurrentSystemDemandTS": null,
  "currentSolar": 1240,
  "renewablesPercentwoBatteries": 28,
  "OutageDTS": null,
  "currentCo2": 6893,
  "todayForecastPeakDemand": 26719
}
